boldigger/__init__.py
boldigger/__main__.py
boldigger/additional_data.py
boldigger/api_verification.py
boldigger/boldblast_coi.py
boldigger/boldblast_its.py
boldigger/boldblast_rbcl.py
boldigger/check_fasta.py
boldigger/digger_sort.py
boldigger/first_hit.py
boldigger/jamp_hit.py
boldigger/login.py
boldigger/data/certs.pem
boldigger/data/github.png
boldigger/data/logo.png
boldigger/data/userdata
boldigger-2.2.2.dist-info/LICENSE
boldigger-2.2.2.dist-info/METADATA
boldigger-2.2.2.dist-info/WHEEL
boldigger-2.2.2.dist-info/entry_points.txt
boldigger-2.2.2.dist-info/top_level.txt
boldigger-2.2.2.dist-info/RECORD
