Metadata-Version: 2.1
Name: boldigger
Version: 2.2.2
Summary: A python package to query different databases of boldsystems.org
Home-page: https://github.com/DominikBuchner/BOLDigger
Author: Dominik Buchner
Author-email: dominik.buchner524@googlemail.com
License: MIT
Classifier: Programming Language :: Python :: 3
Classifier: License :: OSI Approved :: MIT License
Classifier: Operating System :: OS Independent
Requires-Python: >=3.6
License-File: LICENSE
Requires-Dist: PySimpleGUI >=4.18.2
Requires-Dist: requests-html >=0.10.0
Requires-Dist: beautifulsoup4 >=4.7.1
Requires-Dist: openpyxl >=2.6.2
Requires-Dist: numpy >=1.16.4
Requires-Dist: pandas >=0.25.0
Requires-Dist: requests >=2.22.0
Requires-Dist: more-itertools >=7.2.0
Requires-Dist: lxml >=4.3.3
Requires-Dist: html5lib >=1.0.1
Requires-Dist: xlrd >=1.2.0
Requires-Dist: luddite >=1.0.1
Requires-Dist: biopython >=1.78
Requires-Dist: joblib >=1.1.0
Requires-Dist: psutil >=5.8.0
Requires-Dist: tqdm >=4.56.0
Requires-Dist: tables >=3.7.0
